setup.cfg
setup.py
pypiece/__init__.py
pypiece/pypiece.py
pypiece.egg-info/PKG-INFO
pypiece.egg-info/SOURCES.txt
pypiece.egg-info/dependency_links.txt
pypiece.egg-info/entry_points.txt
pypiece.egg-info/requires.txt
pypiece.egg-info/top_level.txt