Metadata-Version: 1.1
Name: pypiece
Version: 0.1.3.1
Summary: Wrapper around pip for flakey connections.
Home-page: https://github.com/lensvol/pypiece
Author: Kirill Borisov
Author-email: lensvol@gmail.com
License: MIT
Keywords: pip
Platform: UNKNOWN
Classifier: Development Status :: 3 - Alpha
Classifier: Topic :: Utilities
Classifier: License :: OSI Approved :: BSD License
